openplx/Core.py
openplx/DriveTrain.py
openplx/Math.py
openplx/Physics.py
openplx/Physics1D.py
openplx/Physics3D.py
openplx/Robotics.py
openplx/Simulation.py
openplx/Terrain.py
openplx/Urdf.py
openplx/Vehicles.py
openplx/Visuals.py
openplx/_AgxOpenPlxPyApi.cpython-39-darwin.so
openplx/_CorePythonSwig.cpython-39-darwin.so
openplx/_DriveTrainSwig.cpython-39-darwin.so
openplx/_MathSwig.cpython-39-darwin.so
openplx/_Physics1DSwig.cpython-39-darwin.so
openplx/_Physics3DSwig.cpython-39-darwin.so
openplx/_PhysicsSwig.cpython-39-darwin.so
openplx/_RoboticsSwig.cpython-39-darwin.so
openplx/_SimulationSwig.cpython-39-darwin.so
openplx/_TerrainSwig.cpython-39-darwin.so
openplx/_UrdfSwig.cpython-39-darwin.so
openplx/_VehiclesSwig.cpython-39-darwin.so
openplx/_VisualsSwig.cpython-39-darwin.so
openplx/__init__.py
openplx/agxtoopenplx.py
openplx/anytoopenplx.py
openplx/api.py
openplx/migrate.py
openplx/migration_hint.py
openplx/migrations.py
openplx/openplx_application.py
openplx/openplx_serialize.py
openplx/openplx_validate.py
openplx/openplx_view.py
openplx/versionaction.py
agx_openplx-0.16.10.dist-info/METADATA
agx_openplx-0.16.10.dist-info/WHEEL
agx_openplx-0.16.10.dist-info/entry_points.txt
agx_openplx-0.16.10.dist-info/RECORD
