Metadata-Version: 2.1
Name: agx-openplx
Version: 0.16.10
Summary: AGX-OpenPLX python interface development
Home-page: https://pub.algoryx.dev/openplx/
License: Apache 2.0
Author: Algoryx
Author-email: algoryx@algoryx.com
Requires-Python: >=3.8
Classifier: Intended Audience :: Manufacturing
Classifier: Intended Audience :: Science/Research
Classifier: License :: Other/Proprietary License
Classifier: Programming Language :: Python :: 3
Classifier: Programming Language :: Python :: 3.8
Classifier: Programming Language :: Python :: 3.9
Classifier: Programming Language :: Python :: 3.10
Classifier: Programming Language :: Python :: 3.11
Classifier: Topic :: Scientific/Engineering :: Physics
Classifier: Topic :: Scientific/Engineering :: Visualization
Requires-Dist: agx (==2.39.1.2)
Requires-Dist: openplx-bundles (>=0.16.10,<0.17.0)
Requires-Dist: pclick (>=0.5.1,<0.6.0)
